video2story/__init__.py
video2story/__main__.py
video2story/cutter.py
video2story/uploader.py
video2story-1.1.0.dist-info/LICENSE
video2story-1.1.0.dist-info/METADATA
video2story-1.1.0.dist-info/WHEEL
video2story-1.1.0.dist-info/entry_points.txt
video2story-1.1.0.dist-info/RECORD
