Metadata-Version: 2.1
Name: video2story
Version: 1.1.0
Summary: Simple telegram story uploader
Home-page: https://codeberg.org/igorechek06/video2story
Author: Tolmachev Igor
Author-email: me@igorek.dev
Requires-Python: >=3.10,<4.0
Classifier: Programming Language :: Python :: 3
Classifier: Programming Language :: Python :: 3.10
Classifier: Programming Language :: Python :: 3.11
Classifier: Programming Language :: Python :: 3.12
Requires-Dist: python-telegram (>=0.19.0,<0.20.0)
Project-URL: Repository, https://codeberg.org/igorechek06/video2story
